{
  "props": {
    "shadowBox": false,
    "width": "full",
    "margin": false
  },
  "items": [
    {
      "type": "standard-banner-v2",
      "order": "1",
      "props": {
        "backgroundImage": {
          "desktop" : {
            "source": "https://cdn.ship.schibsted.io/api/v1/ship-static/images/07/0750d7a4-943d-4e9d-a6b8-e17393f0c8ad?rule=original",
            "alt": "Gå ner i vikt snabbt och enkelt"
          },
          "tablet": {
            "source": "https://cdn.ship.schibsted.io/api/v1/ship-static/images/5a/5a3993b7-737a-4a68-9d65-140eb1a0c32a?rule=original",
            "alt": "Gå ner i vikt snabbt och enkelt"
          },
          "mobile": {
            "source": "https://cdn.ship.schibsted.io/api/v1/ship-static/images/72/726e873d-a7e4-4b9a-9c41-ee8895e29157?rule=original",
            "alt": "Gå ner i vikt snabbt och enkelt"
          }
        },
        "topOffset": 200,
        "bulletList": [
          "Vanlig, fräsch och nyttig mat",
          "Stöd från experter och medlemmar",
          "Loggboken håller koll på kalorierna"
        ],
        "bulletListHeader": "Ett personligt viktminskningsprogram skapat utifrån dina förutsättningar och mål",
        "header": "Nå din målvikt med oss",
        "ctaHref": "/kampanj/blimedlem",
        "ctaLabel": {
          "desktop": "Börja idag",
          "tablet": "Börja idag",
          "mobile": "Börja idag"
        },
        "ctaFootnote": "",
        "body": "",
        "bodyEmphasizeTitle": "",
        "bodyEmphasizeText": "Du får loggbok, träningsprogram och kaloriberäknade recept",
        "topNoteText": "",
        "topNoteLink": "",
        "topNoteLinkText": "",
        "feedDesc": ""
      }
    }
  ]
}
